spinsrv/__init__.py
spinsrv/spin.py
spinsrv/spinfs.py
spinsrv/spinpy.py
spinsrv/_data/__init__.py
spinsrv/_data/bit_ops.py
spinsrv/_data/bit_server.py
spinsrv/_data/dir_ops.py
spinsrv/_data/dir_server.py
spinsrv/_data/entries.py
spinsrv/_data/entry_blocks.py
spinsrv/_data/entry_levels.py
spinsrv/_data/entry_types.py
spinsrv/_data/entry_versions.py
spinsrv/_data/license_types.py
spinsrv/_data/licenses.py
spinsrv/_data/pack_types.py
spinsrv/_data/path_patterns.py
spinsrv/_data/permission_grant_types.py
spinsrv/_data/permission_grants.py
spinsrv/_data/permissions.py
spinsrv/_data/store.py
spinsrv/_data/_client/__init__.py
spinsrv/_data/_client/client.py
spinsrv/_data/_client/file.py
spinsrv/_data/_client/file_system.py
spinsrv/_identity/__init__.py
spinsrv/_identity/aliases.py
spinsrv/_identity/factor_server.py
spinsrv/_identity/factor_types.py
spinsrv/_identity/factorization_types.py
spinsrv/_identity/factorizations.py
spinsrv/_identity/factors.py
spinsrv/_identity/key_server.py
spinsrv/_identity/key_types.py
spinsrv/_identity/keys.py
spinsrv/_identity/py.typed
spinsrv/_identity/test_smoke.py
spinsrv/_spin/__init__.py
spinsrv/_spin/paths.py
spinsrv/_spin/py.typed
spinsrv/_spin/spin.py
spinsrv/_spin/test_times.py
spinsrv/_spin/times.py
spinsrv-0.0.19.dist-info/METADATA
spinsrv-0.0.19.dist-info/WHEEL
spinsrv-0.0.19.dist-info/RECORD
