Metadata-Version: 2.1
Name: spinsrv
Version: 0.0.19
Summary: The spin python package. See https://spinsrv.com
Project-URL: Homepage, https://github.com/spinsrv/spinpy
Author-email: "N. C. Landolfi" <crews.fixture.0f@icloud.com>
Classifier: License :: OSI Approved :: MIT License
Classifier: Operating System :: OS Independent
Classifier: Programming Language :: Python :: 3
Requires-Python: >=3.7
Requires-Dist: fsspec==2022.11.0
Requires-Dist: python-dateutil
Requires-Dist: requests
